lusbir.py
shape_warrior_t.lusbir-1.0.0.dist-info/LICENSE
shape_warrior_t.lusbir-1.0.0.dist-info/METADATA
shape_warrior_t.lusbir-1.0.0.dist-info/WHEEL
shape_warrior_t.lusbir-1.0.0.dist-info/top_level.txt
shape_warrior_t.lusbir-1.0.0.dist-info/RECORD
