Metadata-Version: 2.1
Name: shape-warrior-t.lusbir
Version: 1.0.0
Summary: An alternative conception of integer ranges in Python.
Author-email: Bonan Luan <bl.swt1@gmail.com>
Project-URL: GitHub, https://github.com/shape-warrior-t/lusbir
Classifier: Programming Language :: Python :: 3
Classifier: License :: OSI Approved :: MIT License
Classifier: Operating System :: OS Independent
Requires-Python: >=3.10
License-File: LICENSE
